cloudflared_tunnel.py
cloudflared_tunnel-0.1.0.dist-info/LICENSE
cloudflared_tunnel-0.1.0.dist-info/METADATA
cloudflared_tunnel-0.1.0.dist-info/WHEEL
cloudflared_tunnel-0.1.0.dist-info/top_level.txt
cloudflared_tunnel-0.1.0.dist-info/RECORD
