Metadata-Version: 2.1
Name: cloudflared-tunnel
Version: 0.1.0
Summary: Start a TryCloudflare Tunnel with a context manager.
Home-page: https://github.com/UWUplus/soldni/python-cloudflare-tunnel
Author: Ralf Rademacher and Luca Soldaini
Keywords: cloudflare tunnel python
Classifier: Programming Language :: Python :: 3.8
Classifier: License :: OSI Approved :: Apache Software License
Classifier: Operating System :: OS Independent
License-File: LICENSE
Requires-Dist: requests
